MANIFEST.in
README.md
cfast_slic.pxd
cfast_slic.pyx
csimple_crf.pyx
setup.py
cpuid/__init__.py
cpuid/cpuid.py
fast_slic/__init__.py
fast_slic/avx2.py
fast_slic/base_slic.py
fast_slic/crf.py
fast_slic/neon.py
fast_slic.egg-info/PKG-INFO
fast_slic.egg-info/SOURCES.txt
fast_slic.egg-info/dependency_links.txt
fast_slic.egg-info/requires.txt
fast_slic.egg-info/top_level.txt
src/cca.cpp
src/cca.h
src/cielab.h
src/context-impl.cpp
src/context.cpp
src/context.h
src/fast-slic-common.h
src/fast-slic.cpp
src/fast-slic.h
src/kdtree.h
src/lsc-builder.cpp
src/lsc.cpp
src/lsc.h
src/parallel.cpp
src/parallel.h
src/preemptive.h
src/recorder.h
src/simd-helper.hpp
src/simple-crf.cpp
src/simple-crf.h
src/simple-crf.hpp
src/timer.cpp
src/timer.h
src/arch/arm/neon.h
src/arch/x64/avx2.h
src/cpptest/main.cpp
src/cpptest/test_cca.cpp
src/cpptest/test_cielab.cpp
test/test_crf.py
test/test_slic.py