Metadata-Version: 1.2
Name: fast-slic
Version: 0.4.0
Summary: Fast Slic Superpixel Implementation
Home-page: UNKNOWN
Author: Alchan Kim
Author-email: a9413miky@gmail.com
License: MIT
Platform: UNKNOWN
Classifier: License :: OSI Approved :: MIT License
Classifier: Programming Language :: Python
Classifier: Programming Language :: Python :: 3.5
Classifier: Programming Language :: Python :: 3.6
Classifier: Programming Language :: Python :: 3.7
Classifier: Programming Language :: Python :: Implementation :: CPython
Requires-Python: >=3.5
